mcp_gotify/__init__.py
mcp_gotify/config.py
mcp_gotify/main.py
mcp_gotify_fastmcp-0.1.2.dist-info/METADATA
mcp_gotify_fastmcp-0.1.2.dist-info/WHEEL
mcp_gotify_fastmcp-0.1.2.dist-info/entry_points.txt
mcp_gotify_fastmcp-0.1.2.dist-info/licenses/LICENSE
mcp_gotify_fastmcp-0.1.2.dist-info/RECORD
